SpoofMailer/__init__.py
SpoofMailer-1.0.0.dist-info/DESCRIPTION.rst
SpoofMailer-1.0.0.dist-info/METADATA
SpoofMailer-1.0.0.dist-info/RECORD
SpoofMailer-1.0.0.dist-info/WHEEL
SpoofMailer-1.0.0.dist-info/metadata.json
SpoofMailer-1.0.0.dist-info/top_level.txt
