Metadata-Version: 2.0
Name: SpoofMailer
Version: 1.0.0
Summary: By ussing SpoofMailer you can send unlimited spoof email or make your own mailing server API
Home-page: https://github.com/Dipankershah/SpoofMailer
Author: Dipanker shah
Author-email: Dipankarshah143@gmail.com
License: UNKNOWN
Platform: UNKNOWN
Classifier: Programming Language :: Python :: 3
Classifier: License :: OSI Approved :: MIT License
Classifier: Operating System :: OS Independent
Requires-Dist: requests
